ciscoconfparse/__init__.py
ciscoconfparse/__main__.py
ciscoconfparse/ccp_abc.py
ciscoconfparse/ccp_util.py
ciscoconfparse/ciscoconfparse.py
ciscoconfparse/errors.py
ciscoconfparse/models_asa.py
ciscoconfparse/models_cisco.py
ciscoconfparse/models_iosxr.py
ciscoconfparse/models_junos.py
ciscoconfparse/models_nxos.py
ciscoconfparse/protocol_values.py
tests/conftest.py
tests/performance_case.py
tests/runtests.sh
tests/test_Ccp_Abc.py
tests/test_Ccp_Util.py
tests/test_CiscoConfParse.py
tests/test_Models_Asa.py
tests/test_Models_Cisco.py
tests/test_Models_Junos.py
ciscoconfparse-1.9.50.dist-info/LICENSE
ciscoconfparse-1.9.50.dist-info/METADATA
ciscoconfparse-1.9.50.dist-info/WHEEL
ciscoconfparse-1.9.50.dist-info/RECORD
