Metadata-Version: 2.1
Name: ciscoconfparse
Version: 1.9.50
Summary: Parse, Audit, Query, Build, and Modify Cisco IOS-style and JunOS-style configs
License: GPL-3.0-only
Keywords: Parse,audit,query,modify,Cisco IOS,Cisco,NXOS,ASA,Juniper
Author: Mike Pennington
Author-email: mike@pennington.net
Maintainer: Mike Pennington
Maintainer-email: mike@pennington.net
Requires-Python: >=3.8,<4.0.0
Classifier: Development Status :: 5 - Production/Stable
Classifier: Environment :: Plugins
Classifier: Intended Audience :: Developers
Classifier: Intended Audience :: Information Technology
Classifier: Intended Audience :: System Administrators
Classifier: Intended Audience :: Telecommunications Industry
Classifier: License :: OSI Approved :: GNU General Public License (GPL)
Classifier: License :: OSI Approved :: GNU General Public License v3 (GPLv3)
Classifier: Natural Language :: English
Classifier: Operating System :: OS Independent
Classifier: Programming Language :: Python
Classifier: Programming Language :: Python :: 3
Classifier: Programming Language :: Python :: 3.8
Classifier: Programming Language :: Python :: 3.9
Classifier: Programming Language :: Python :: 3.10
Classifier: Programming Language :: Python :: 3.11
Classifier: Programming Language :: Python :: 3.12
Classifier: Topic :: Communications
Classifier: Topic :: Internet
Classifier: Topic :: System :: Networking
Classifier: Topic :: System :: Networking :: Monitoring
Requires-Dist: deprecated (>=1.2.14)
Requires-Dist: dnspython (>=2.4.2,<3.0.0)
Requires-Dist: hier_config (>=2.2.2)
Requires-Dist: loguru (==0.7.2)
Requires-Dist: passlib (>=1.7.4,<2.0.0)
Requires-Dist: toml (>=0.10.2)
Project-URL: documentation, http://www.pennington.net/py/ciscoconfparse/
Project-URL: homepage, http://www.pennington.net/py/ciscoconfparse/
Project-URL: repository, https://github.com/mpenning/ciscoconfparse
Project-URL: source, https://github.com/mpenning/ciscoconfparse
